biosimulators_opencor/__init__.py
biosimulators_opencor/__main__.py
biosimulators_opencor/_version.py
biosimulators_opencor/core.py
biosimulators_opencor/data_model.py
biosimulators_opencor/utils.py
biosimulators_opencor-0.0.13.dist-info/LICENSE
biosimulators_opencor-0.0.13.dist-info/METADATA
biosimulators_opencor-0.0.13.dist-info/WHEEL
biosimulators_opencor-0.0.13.dist-info/entry_points.txt
biosimulators_opencor-0.0.13.dist-info/top_level.txt
biosimulators_opencor-0.0.13.dist-info/RECORD
