Metadata-Version: 2.1
Name: biosimulators-opencor
Version: 0.0.13
Summary: BioSimulators-compliant command-line interface to the OpenCOR simulation program.
Home-page: https://github.com/biosimulators/Biosimulators_OpenCOR
Author: BioSimulators Team
Author-email: info@biosimulators.org
License: MIT
Download-URL: https://github.com/biosimulators/Biosimulators_OpenCOR
Keywords: systems biology,computational biology,CellML,SED-ML,BioSimulators,COMBINE,OMEX,OpenCOR
Platform: UNKNOWN
Classifier: Development Status :: 3 - Alpha
Classifier: Intended Audience :: Science/Research
Classifier: License :: OSI Approved :: MIT License
Classifier: Topic :: Scientific/Engineering :: Bio-Informatics
License-File: LICENSE
Requires-Dist: biosimulators-utils[cellml,logging] (>=0.1.155)
Requires-Dist: kisao (>=2.28)
Requires-Dist: lxml
Requires-Dist: numpy
Provides-Extra: all
Requires-Dist: python-dateutil ; extra == 'all'
Provides-Extra: docs
Provides-Extra: tests
Requires-Dist: python-dateutil ; extra == 'tests'
